README.rst
setup.py
tornado_msgpack/__init__.py
tornado_msgpack/client.py
tornado_msgpack/dispatcher.py
tornado_msgpack/server.py
tornado_msgpack/session.py
tornado_msgpack.egg-info/PKG-INFO
tornado_msgpack.egg-info/SOURCES.txt
tornado_msgpack.egg-info/dependency_links.txt
tornado_msgpack.egg-info/requires.txt
tornado_msgpack.egg-info/top_level.txt