Metadata-Version: 1.1
Name: tornado-msgpack
Version: 0.4
Summary: ore ore MessagePack RPC
Home-page: UNKNOWN
Author: ousttrue
Author-email: ousttrue@gmail.com
License: Apache Software License
Platform: UNKNOWN
Classifier: Programming Language :: Python :: 3
Classifier: License :: OSI Approved :: Apache Software License
